{"cameraMode":{"drawMode":0,"name":"Shaded","section":"Shading Mode"},"sceneLighting":true,"audioPlay":false,"sceneViewState":{"showFog":true,"showMaterialUpdate":false,"showSkybox":true,"showFlares":true,"showImageEffects":true,"showParticleSystems":true},"in2DMode":false,"pivot":{"x":7.135029315948486,"y":-3.4945685863494875,"z":0.7348108291625977},"rotation":{"x":0.017023395746946336,"y":0.9145766496658325,"z":-0.4021988809108734,"w":0.03871080279350281},"size":8.001471519470215,"orthographic":false}