{"cameraMode":{"drawMode":0,"name":"Shaded","section":"Shading Mode"},"sceneLighting":true,"audioPlay":false,"sceneViewState":{"showFog":true,"showMaterialUpdate":false,"showSkybox":true,"showFlares":true,"showImageEffects":true,"showParticleSystems":true},"in2DMode":false,"pivot":{"x":-0.9887228012084961,"y":-0.28966760635375979,"z":-2.301342487335205},"rotation":{"x":-0.0030791391618549825,"y":0.9352222681045532,"z":-0.35395392775535586,"w":-0.008135737851262093},"size":10.0,"orthographic":false}